pydbhub/__init__.py
pydbhub/dbhub.py
pydbhub/httphub.py
pydbhub/py.typed
pydbhub_bjh-0.0.9.dist-info/LICENSE
pydbhub_bjh-0.0.9.dist-info/WHEEL
pydbhub_bjh-0.0.9.dist-info/METADATA
pydbhub_bjh-0.0.9.dist-info/RECORD
