Metadata-Version: 2.1
Name: pydbhub-bjh
Version: 0.0.9
Summary: pydbhub
Author-email: LeMoussel <cnhx27@gmail.com>
Requires-Python: >=3.7
Classifier: License :: OSI Approved :: MIT License
Requires-Dist: requests
Requires-Dist: python_dateutil
Requires-Dist: rich
